skeptofox/__init__.py
skeptofox/agent.py
skeptofox-0.1.1.dist-info/METADATA
skeptofox-0.1.1.dist-info/WHEEL
skeptofox-0.1.1.dist-info/licenses/LICENSE
skeptofox-0.1.1.dist-info/RECORD
