Metadata-Version: 2.4
Name: skeptofox
Version: 0.1.1
Summary: A machine-human intelligence framework for declarative programming, Agentic AI and automation workflows
Project-URL: Homepage, https://github.com/skeptofox/skeptofox
Project-URL: Repository, https://github.com/skeptofox/skeptofox
Project-URL: Bug Tracker, https://github.com/skeptofox/skeptofox/issues
Author-email: skeptofox <skeptofox@gmail.com>
License: MIT License
License-File: LICENSE
Keywords: agentic ai,automation,declarative programming,human-in-the-loop,llm,machine intelligence,sandbox,workflow
Classifier: Development Status :: 3 - Alpha
Classifier: Intended Audience :: Developers
Classifier: Intended Audience :: Science/Research
Classifier: License :: OSI Approved :: MIT License
Classifier: Operating System :: OS Independent
Classifier: Programming Language :: Python :: 3
Classifier: Programming Language :: Python :: 3.8
Classifier: Programming Language :: Python :: 3.9
Classifier: Programming Language :: Python :: 3.10
Classifier: Programming Language :: Python :: 3.11
Classifier: Programming Language :: Python :: 3.12
Classifier: Topic :: Scientific/Engineering :: Artificial Intelligence
Classifier: Topic :: Software Development :: Libraries :: Python Modules
Requires-Python: >=3.8
Requires-Dist: packaging
